{"nodes": [{"id": "gameinitializer", "label": "GameInitializer.cs", "file_type": "code", "source_file": "Client/Scripts/Core/GameInitializer.cs", "source_location": "L1"}, {"id": "gameinitializer_roguelikegame_core", "label": "RoguelikeGame.Core", "file_type": "code", "source_file": "Client/Scripts/Core/GameInitializer.cs", "source_location": "L8"}, {"id": "gameinitializer_gameinitializer", "label": "GameInitializer", "file_type": "code", "source_file": "Client/Scripts/Core/GameInitializer.cs", "source_location": "L10"}, {"id": "node", "label": "Node", "file_type": "code", "source_file": "", "source_location": ""}, {"id": "gameinitializer_gameinitializer_ready", "label": "._Ready()", "file_type": "code", "source_file": "Client/Scripts/Core/GameInitializer.cs", "source_location": "L18"}, {"id": "gameinitializer_gameinitializer_initializemanagers", "label": ".InitializeManagers()", "file_type": "code", "source_file": "Client/Scripts/Core/GameInitializer.cs", "source_location": "L30"}, {"id": "gameinitializer_gameinitializer_startgame", "label": ".StartGame()", "file_type": "code", "source_file": "Client/Scripts/Core/GameInitializer.cs", "source_location": "L59"}, {"id": "gameinitializer_gameinitializer_quickstart", "label": ".QuickStart()", "file_type": "code", "source_file": "Client/Scripts/Core/GameInitializer.cs", "source_location": "L65"}], "edges": [{"source": "gameinitializer", "target": "godot", "relation": "imports", "confidence": "EXTRACTED", "source_file": "Client/Scripts/Core/GameInitializer.cs", "source_location": "L1", "weight": 1.0}, {"source": "gameinitializer", "target": "system", "relation": "imports", "confidence": "EXTRACTED", "source_file": "Client/Scripts/Core/GameInitializer.cs", "source_location": "L2", "weight": 1.0}, {"source": "gameinitializer", "target": "core", "relation": "imports", "confidence": "EXTRACTED", "source_file": "Client/Scripts/Core/GameInitializer.cs", "source_location": "L3", "weight": 1.0}, {"source": "gameinitializer", "target": "systems", "relation": "imports", "confidence": "EXTRACTED", "source_file": "Client/Scripts/Core/GameInitializer.cs", "source_location": "L4", "weight": 1.0}, {"source": "gameinitializer", "target": "generation", "relation": "imports", "confidence": "EXTRACTED", "source_file": "Client/Scripts/Core/GameInitializer.cs", "source_location": "L5", "weight": 1.0}, {"source": "gameinitializer", "target": "packages", "relation": "imports", "confidence": "EXTRACTED", "source_file": "Client/Scripts/Core/GameInitializer.cs", "source_location": "L6", "weight": 1.0}, {"source": "gameinitializer", "target": "gameinitializer_roguelikegame_core", "relation": "contains", "confidence": "EXTRACTED", "source_file": "Client/Scripts/Core/GameInitializer.cs", "source_location": "L8", "weight": 1.0}, {"source": "gameinitializer", "target": "gameinitializer_gameinitializer", "relation": "contains", "confidence": "EXTRACTED", "source_file": "Client/Scripts/Core/GameInitializer.cs", "source_location": "L10", "weight": 1.0}, {"source": "gameinitializer_gameinitializer", "target": "node", "relation": "inherits", "confidence": "EXTRACTED", "source_file": "Client/Scripts/Core/GameInitializer.cs", "source_location": "L10", "weight": 1.0}, {"source": "gameinitializer_gameinitializer", "target": "gameinitializer_gameinitializer_ready", "relation": "method", "confidence": "EXTRACTED", "source_file": "Client/Scripts/Core/GameInitializer.cs", "source_location": "L18", "weight": 1.0}, {"source": "gameinitializer_gameinitializer", "target": "gameinitializer_gameinitializer_initializemanagers", "relation": "method", "confidence": "EXTRACTED", "source_file": "Client/Scripts/Core/GameInitializer.cs", "source_location": "L30", "weight": 1.0}, {"source": "gameinitializer_gameinitializer", "target": "gameinitializer_gameinitializer_startgame", "relation": "method", "confidence": "EXTRACTED", "source_file": "Client/Scripts/Core/GameInitializer.cs", "source_location": "L59", "weight": 1.0}, {"source": "gameinitializer_gameinitializer", "target": "gameinitializer_gameinitializer_quickstart", "relation": "method", "confidence": "EXTRACTED", "source_file": "Client/Scripts/Core/GameInitializer.cs", "source_location": "L65", "weight": 1.0}, {"source": "gameinitializer_gameinitializer_ready", "target": "gameinitializer_gameinitializer_initializemanagers", "relation": "calls", "confidence": "EXTRACTED", "source_file": "Client/Scripts/Core/GameInitializer.cs", "source_location": "L22", "weight": 1.0}]}